[
  {
    "name": "田中 太郎",
    "position": "代表取締役 CEO",
    "bio": "製造業界で20年以上の経験を持つ省エネエキスパート。工学博士。大手製造業での省エネプロジェクトを多数成功に導いた実績を持つ。",
    "image": "/team/tanaka.jpg",
    "qualifications": ["エネルギー管理士", "環境計量士", "工学博士"],
    "experience": "20年以上"
  },
  {
    "name": "佐藤 花子",
    "position": "CTO",
    "bio": "環境工学のスペシャリスト。AIを活用した省エネソリューションの開発をリード。東京大学環境工学科卒業。",
    "image": "/team/sato.jpg",
    "qualifications": ["技術士（環境）", "公害防止管理者", "環境カウンセラー"],
    "experience": "15年以上"
  },
  {
    "name": "山田 次郎",
    "position": "シニアコンサルタント",
    "bio": "中小製造業に特化したコンサルティング実績200社以上。現場での実務経験豊富なエキスパート。",
    "image": "/team/yamada.jpg",
    "qualifications": ["エネルギー管理士", "診断士", "ISO14001審査員"],
    "experience": "18年以上"
  },
  {
    "name": "鈴木 美咲",
    "position": "プロジェクトマネージャー",
    "bio": "プロジェクト管理のスペシャリスト。お客様との円滑なコミュニケーションと確実な成果創出を担当。",
    "image": "/team/suzuki.jpg",
    "qualifications": ["PMP", "中小企業診断士", "簿記1級"],
    "experience": "12年以上"
  }
]